trytoncommunity_setuptools/__init__.py
trytoncommunity_setuptools-0.4.1.dist-info/METADATA
trytoncommunity_setuptools-0.4.1.dist-info/WHEEL
trytoncommunity_setuptools-0.4.1.dist-info/top_level.txt
trytoncommunity_setuptools-0.4.1.dist-info/RECORD
