Metadata-Version: 2.4
Name: trytoncommunity-setuptools
Version: 0.4.1
Summary: Shortening the boilerplate in Tryton modules
Home-page: https://tryton.community
Author: Hartmut Goebel
Author-email: h.goebel@crazy-compilers.com
License: GPL-3.0-or-later
Project-URL: Source Code, https://foss.heptapod.net/tryton-community/setuptools
Keywords: tryton,setuptools,package management
Classifier: Development Status :: 3 - Alpha
Classifier: Framework :: Tryton
Classifier: Intended Audience :: Developers
Classifier: License :: OSI Approved :: GNU General Public License v3 or later (GPLv3+)
Classifier: Operating System :: OS Independent
Classifier: Programming Language :: Python :: 3
Classifier: Programming Language :: Python :: 3 :: Only
Classifier: Topic :: Software Development :: Libraries :: Python Modules
Classifier: Topic :: System :: Archiving :: Packaging
Classifier: Topic :: System :: Systems Administration
Classifier: Topic :: Utilities
Requires-Python: >=3.6
Requires-Dist: setuptools
